{
  "code": 200,
  "data": [
    {
      "aliasEnglishValue": "beijing",
      "aliasPinYinValue": "beijing",
      "children": [],
      "deleted": "UNDELETED",
      "desc": "",
      "id": 2881,
      "intKey": 530,
      "itemAliasValue1": null,
      "itemAliasValue2": null,
      "order": 1,
      "parentIntKey": 0,
      "parentStrKey": "0",
      "strKey": "530",
      "value": "北京"
    },
    {
      "aliasEnglishValue": "tianjin",
      "aliasPinYinValue": "tianjin",
      "children": [],
      "deleted": "UNDELETED",
      "desc": "",
      "id": 2885,
      "intKey": 531,
      "itemAliasValue1": null,
      "itemAliasValue2": null,
      "order": 5,
      "parentIntKey": 0,
      "parentStrKey": "0",
      "strKey": "531",
      "value": "天津"
    },
    {
      "aliasEnglishValue": "shanghai",
      "aliasPinYinValue": "shanghai",
      "children": [],
      "deleted": "UNDELETED",
      "desc": "",
      "id": 2882,
      "intKey": 538,
      "itemAliasValue1": null,
      "itemAliasValue2": null,
      "order": 2,
      "parentIntKey": 0,
      "parentStrKey": "0",
      "strKey": "538",
      "value": "上海"
    },
    {
      "aliasEnglishValue": "chongqing",
      "aliasPinYinValue": "chongqing",
      "children": [],
      "deleted": "UNDELETED",
      "desc": "",
      "id": 2899,
      "intKey": 551,
      "itemAliasValue1": null,
      "itemAliasValue2": null,
      "order": 19,
      "parentIntKey": 0,
      "parentStrKey": "0",
      "strKey": "551",
      "value": "重庆"
    },
    {
      "aliasEnglishValue": "shijiazhuang",
      "aliasPinYinValue": "shijiazhuang",
      "children": [],
      "deleted": "UNDELETED",
      "desc": "",
      "id": 2905,
      "intKey": 565,
      "itemAliasValue1": null,
      "itemAliasValue2": null,
      "order": 25,
      "parentIntKey": 0,
      "parentStrKey": "0",
      "strKey": "565",
      "value": "石家庄"
    },
    {
      "aliasEnglishValue": "taiyuan",
      "aliasPinYinValue": "taiyuan",
      "children": [],
      "deleted": "UNDELETED",
      "desc": "",
      "id": 2908,
      "intKey": 576,
      "itemAliasValue1": null,
      "itemAliasValue2": null,
      "order": 28,
      "parentIntKey": 0,
      "parentStrKey": "0",
      "strKey": "576",
      "value": "太原"
    },
    {
      "aliasEnglishValue": "shenyang",
      "aliasPinYinValue": "shenyang",
      "children": [],
      "deleted": "UNDELETED",
      "desc": "",
      "id": 2891,
      "intKey": 599,
      "itemAliasValue1": null,
      "itemAliasValue2": null,
      "order": 11,
      "parentIntKey": 0,
      "parentStrKey": "0",
      "strKey": "599",
      "value": "沈阳"
    },
    {
      "aliasEnglishValue": "dalian",
      "aliasPinYinValue": "dalian",
      "children": [],
      "deleted": "UNDELETED",
      "desc": "",
      "id": 2889,
      "intKey": 600,
      "itemAliasValue1": null,
      "itemAliasValue2": null,
      "order": 9,
      "parentIntKey": 0,
      "parentStrKey": "0",
      "strKey": "600",
      "value": "大连"
    },
    {
      "aliasEnglishValue": "changchun",
      "aliasPinYinValue": "changchun",
      "children": [],
      "deleted": "UNDELETED",
      "desc": "",
      "id": 2890,
      "intKey": 613,
      "itemAliasValue1": null,
      "itemAliasValue2": null,
      "order": 10,
      "parentIntKey": 0,
      "parentStrKey": "0",
      "strKey": "613",
      "value": "长春"
    },
    {
      "aliasEnglishValue": "haerbin",
      "aliasPinYinValue": "haerbin",
      "children": [],
      "deleted": "UNDELETED",
      "desc": "",
      "id": 2904,
      "intKey": 622,
      "itemAliasValue1": null,
      "itemAliasValue2": null,
      "order": 24,
      "parentIntKey": 0,
      "parentStrKey": "0",
      "strKey": "622",
      "value": "哈尔滨"
    },
    {
      "aliasEnglishValue": "nanjing",
      "aliasPinYinValue": "nanjing",
      "children": [],
      "deleted": "UNDELETED",
      "desc": "",
      "id": 2892,
      "intKey": 635,
      "itemAliasValue1": null,
      "itemAliasValue2": null,
      "order": 12,
      "parentIntKey": 0,
      "parentStrKey": "0",
      "strKey": "635",
      "value": "南京"
    },
    {
      "aliasEnglishValue": "wuxi",
      "aliasPinYinValue": "wuxi",
      "children": [],
      "deleted": "UNDELETED",
      "desc": "",
      "id": 2897,
      "intKey": 636,
      "itemAliasValue1": null,
      "itemAliasValue2": null,
      "order": 17,
      "parentIntKey": 0,
      "parentStrKey": "0",
      "strKey": "636",
      "value": "无锡"
    },
    {
      "aliasEnglishValue": "suzhou",
      "aliasPinYinValue": "suzhou",
      "children": [],
      "deleted": "UNDELETED",
      "desc": "",
      "id": 2896,
      "intKey": 639,
      "itemAliasValue1": null,
      "itemAliasValue2": null,
      "order": 16,
      "parentIntKey": 0,
      "parentStrKey": "0",
      "strKey": "639",
      "value": "苏州"
    },
    {
      "aliasEnglishValue": "hangzhou",
      "aliasPinYinValue": "hangzhou",
      "children": [],
      "deleted": "UNDELETED",
      "desc": "",
      "id": 2895,
      "intKey": 653,
      "itemAliasValue1": null,
      "itemAliasValue2": null,
      "order": 15,
      "parentIntKey": 0,
      "parentStrKey": "0",
      "strKey": "653",
      "value": "杭州"
    },
    {
      "aliasEnglishValue": "ningbo",
      "aliasPinYinValue": "ningbo",
      "children": [],
      "deleted": "UNDELETED",
      "desc": "",
      "id": 2898,
      "intKey": 654,
      "itemAliasValue1": null,
      "itemAliasValue2": null,
      "order": 18,
      "parentIntKey": 0,
      "parentStrKey": "0",
      "strKey": "654",
      "value": "宁波"
    },
    {
      "aliasEnglishValue": "hefei",
      "aliasPinYinValue": "hefei",
      "children": [],
      "deleted": "UNDELETED",
      "desc": "",
      "id": 2906,
      "intKey": 664,
      "itemAliasValue1": null,
      "itemAliasValue2": null,
      "order": 26,
      "parentIntKey": 0,
      "parentStrKey": "0",
      "strKey": "664",
      "value": "合肥"
    },
    {
      "aliasEnglishValue": "fuzhou",
      "aliasPinYinValue": "fuzhou",
      "children": [],
      "deleted": "UNDELETED",
      "desc": "",
      "id": 2902,
      "intKey": 681,
      "itemAliasValue1": null,
      "itemAliasValue2": null,
      "order": 22,
      "parentIntKey": 0,
      "parentStrKey": "0",
      "strKey": "681",
      "value": "福州"
    },
    {
      "aliasEnglishValue": "xiamen",
      "aliasPinYinValue": "xiamen",
      "children": [],
      "deleted": "UNDELETED",
      "desc": "",
      "id": 2903,
      "intKey": 682,
      "itemAliasValue1": null,
      "itemAliasValue2": null,
      "order": 23,
      "parentIntKey": 0,
      "parentStrKey": "0",
      "strKey": "682",
      "value": "厦门"
    },
    {
      "aliasEnglishValue": "nanchang",
      "aliasPinYinValue": "nanchang",
      "children": [],
      "deleted": "UNDELETED",
      "desc": "",
      "id": 2912,
      "intKey": 691,
      "itemAliasValue1": null,
      "itemAliasValue2": null,
      "order": 32,
      "parentIntKey": 0,
      "parentStrKey": "0",
      "strKey": "691",
      "value": "南昌"
    },
    {
      "aliasEnglishValue": "jinan",
      "aliasPinYinValue": "jinan",
      "children": [],
      "deleted": "UNDELETED",
      "desc": "",
      "id": 2893,
      "intKey": 702,
      "itemAliasValue1": null,
      "itemAliasValue2": null,
      "order": 13,
      "parentIntKey": 0,
      "parentStrKey": "0",
      "strKey": "702",
      "value": "济南"
    },
    {
      "aliasEnglishValue": "qingdao",
      "aliasPinYinValue": "qingdao",
      "children": [],
      "deleted": "UNDELETED",
      "desc": "",
      "id": 2894,
      "intKey": 703,
      "itemAliasValue1": null,
      "itemAliasValue2": null,
      "order": 14,
      "parentIntKey": 0,
      "parentStrKey": "0",
      "strKey": "703",
      "value": "青岛"
    },
    {
      "aliasEnglishValue": "yantai",
      "aliasPinYinValue": "yantai",
      "children": [],
      "deleted": "UNDELETED",
      "desc": "",
      "id": 2910,
      "intKey": 707,
      "itemAliasValue1": null,
      "itemAliasValue2": null,
      "order": 30,
      "parentIntKey": 0,
      "parentStrKey": "0",
      "strKey": "707",
      "value": "烟台"
    },
    {
      "aliasEnglishValue": "zhengzhou",
      "aliasPinYinValue": "zhengzhou",
      "children": [],
      "deleted": "UNDELETED",
      "desc": "",
      "id": 2900,
      "intKey": 719,
      "itemAliasValue1": null,
      "itemAliasValue2": null,
      "order": 20,
      "parentIntKey": 0,
      "parentStrKey": "0",
      "strKey": "719",
      "value": "郑州"
    },
    {
      "aliasEnglishValue": "wuhan",
      "aliasPinYinValue": "wuhan",
      "children": [],
      "deleted": "UNDELETED",
      "desc": "",
      "id": 2886,
      "intKey": 736,
      "itemAliasValue1": null,
      "itemAliasValue2": null,
      "order": 6,
      "parentIntKey": 0,
      "parentStrKey": "0",
      "strKey": "736",
      "value": "武汉"
    },
    {
      "aliasEnglishValue": "zhangsha",
      "aliasPinYinValue": "zhangsha",
      "children": [],
      "deleted": "UNDELETED",
      "desc": "",
      "id": 2901,
      "intKey": 749,
      "itemAliasValue1": null,
      "itemAliasValue2": null,
      "order": 21,
      "parentIntKey": 0,
      "parentStrKey": "0",
      "strKey": "749",
      "value": "长沙"
    },
    {
      "aliasEnglishValue": "guangzhou",
      "aliasPinYinValue": "guangzhou",
      "children": [],
      "deleted": "UNDELETED",
      "desc": "",
      "id": 2883,
      "intKey": 763,
      "itemAliasValue1": null,
      "itemAliasValue2": null,
      "order": 3,
      "parentIntKey": 0,
      "parentStrKey": "0",
      "strKey": "763",
      "value": "广州"
    },
    {
      "aliasEnglishValue": "shenzhen",
      "aliasPinYinValue": "shenzhen",
      "children": [],
      "deleted": "UNDELETED",
      "desc": "",
      "id": 2884,
      "intKey": 765,
      "itemAliasValue1": null,
      "itemAliasValue2": null,
      "order": 4,
      "parentIntKey": 0,
      "parentStrKey": "0",
      "strKey": "765",
      "value": "深圳"
    },
    {
      "aliasEnglishValue": "foshan",
      "aliasPinYinValue": "foshan",
      "children": [],
      "deleted": "UNDELETED",
      "desc": "",
      "id": 2911,
      "intKey": 768,
      "itemAliasValue1": null,
      "itemAliasValue2": null,
      "order": 31,
      "parentIntKey": 0,
      "parentStrKey": "0",
      "strKey": "768",
      "value": "佛山"
    },
    {
      "aliasEnglishValue": "huizhou",
      "aliasPinYinValue": "huizhou",
      "children": [],
      "deleted": "UNDELETED",
      "desc": "",
      "id": 2907,
      "intKey": 773,
      "itemAliasValue1": null,
      "itemAliasValue2": null,
      "order": 27,
      "parentIntKey": 0,
      "parentStrKey": "0",
      "strKey": "773",
      "value": "惠州"
    },
    {
      "aliasEnglishValue": "chengdu",
      "aliasPinYinValue": "chengdu",
      "children": [],
      "deleted": "UNDELETED",
      "desc": "",
      "id": 2888,
      "intKey": 801,
      "itemAliasValue1": null,
      "itemAliasValue2": null,
      "order": 8,
      "parentIntKey": 0,
      "parentStrKey": "0",
      "strKey": "801",
      "value": "成都"
    },
    {
      "aliasEnglishValue": "guiyang",
      "aliasPinYinValue": "guiyang",
      "children": [],
      "deleted": "UNDELETED",
      "desc": "",
      "id": 2913,
      "intKey": 822,
      "itemAliasValue1": null,
      "itemAliasValue2": null,
      "order": 33,
      "parentIntKey": 0,
      "parentStrKey": "0",
      "strKey": "822",
      "value": "贵阳"
    },
    {
      "aliasEnglishValue": "kunming",
      "aliasPinYinValue": "kunming",
      "children": [],
      "deleted": "UNDELETED",
      "desc": "",
      "id": 2909,
      "intKey": 831,
      "itemAliasValue1": null,
      "itemAliasValue2": null,
      "order": 29,
      "parentIntKey": 0,
      "parentStrKey": "0",
      "strKey": "831",
      "value": "昆明"
    },
    {
      "aliasEnglishValue": "xian",
      "aliasPinYinValue": "xian",
      "children": [],
      "deleted": "UNDELETED",
      "desc": "",
      "id": 2887,
      "intKey": 854,
      "itemAliasValue1": null,
      "itemAliasValue2": null,
      "order": 7,
      "parentIntKey": 0,
      "parentStrKey": "0",
      "strKey": "854",
      "value": "西安"
    }
  ],
  "time": "2018-08-14 13:30:44",
  "message": "成功",
  "taskId": "c68b0a30c4054324997a46d97ad7d09c"
}